ploceidae/__init__.py
ploceidae/constants/__init__.py
ploceidae/constants/constants.py
ploceidae/container/__init__.py
ploceidae/container/container.py
ploceidae/container/partial_injection.py
ploceidae/core/__init__.py
ploceidae/core/configurators/__init__.py
ploceidae/core/configurators/basic_configurator.py
ploceidae/dependency/__init__.py
ploceidae/dependency/dependency_locator.py
ploceidae/dependency/dependency_wrapper.py
ploceidae/dependency/dependency_wrapper_helper_methods.py
ploceidae/dependency/garbage_collection/__init__.py
ploceidae/dependency/garbage_collection/garbage_collection_observer.py
ploceidae/dependency/garbage_collection/scheduler.py
ploceidae/dependency_lifetime/__init__.py
ploceidae/dependency_lifetime/dependency_lifetime_enum.py
ploceidae/dependency_lifetime/dependency_lifetime_key.py
ploceidae/dependency_management/__init__.py
ploceidae/dependency_management/cache_item.py
ploceidae/dependency_management/dependency_graph.py
ploceidae/dependency_management/dependency_graph_cycle_check_methods.py
ploceidae/dependency_management/dependency_graph_manager.py
ploceidae/dependency_management/dependency_resolution_methods.py
ploceidae/dependency_management/resolved_dependencies.py
ploceidae/unit_tests/__init__.py
ploceidae/unit_tests/conftest.py
ploceidae/unit_tests/test_configurators.py
ploceidae/unit_tests/test_container.py
ploceidae/unit_tests/test_dependency.py
ploceidae/unit_tests/test_dependency_graph_manager.py
ploceidae/unit_tests/test_dependency_grouping.py
ploceidae/unit_tests/test_dependency_lifetime_management.py
ploceidae/unit_tests/test_dependency_location.py
ploceidae/unit_tests/test_garbage_collection.py
ploceidae/utilities/__init__.py
ploceidae/utilities/dependency_visibility_enum.py
ploceidae/utilities/logging_utilities.py
ploceidae/utilities/module_caches.py
ploceidae/utilities/module_name_helper.py
ploceidae/utilities/reduce_operand.py
ploceidae/utilities/singleton_implementer.py
ploceidae-2.0.36.0.dist-info/LICENSE
ploceidae-2.0.36.0.dist-info/METADATA
ploceidae-2.0.36.0.dist-info/WHEEL
ploceidae-2.0.36.0.dist-info/top_level.txt
ploceidae-2.0.36.0.dist-info/RECORD
