Metadata-Version: 2.1
Name: ploceidae
Version: 2.0.36.0
Summary: dependency injection library
Home-page: https://github.com/MATTHEWFRAZER/ploceidae
Author: Matthew Frazer
Author-email: mfrazeriguess@gmail.com
License: MIT
Keywords: dependency injection DI
Platform: UNKNOWN
Classifier: Programming Language :: Python :: 2.7
Classifier: Programming Language :: Python :: 3.4
Classifier: Programming Language :: Python :: 3.5
Classifier: Programming Language :: Python :: 3.6
Classifier: Programming Language :: Python :: 3.7
Classifier: Programming Language :: Python :: 3.8
Classifier: Programming Language :: Python :: 3.9
License-File: LICENSE
Requires-Dist: PyMonad (==1.3)
Requires-Dist: attrs (==20.3.0)
Requires-Dist: six (==1.12.0)
Requires-Dist: trochilidae (==2.2.0)
